{"v":4,"entries":{"example-table--docs":{"id":"example-table--docs","title":"Example/Table","name":"Docs","importPath":"./packages/component/src/Table/Table.stories.ts","type":"docs","tags":["autodocs","docs"],"storiesImports":[]},"example-table--primary":{"id":"example-table--primary","title":"Example/Table","name":"Primary","importPath":"./packages/component/src/Table/Table.stories.ts","tags":["autodocs","story"],"type":"story"},"example-table--secondary":{"id":"example-table--secondary","title":"Example/Table","name":"Secondary","importPath":"./packages/component/src/Table/Table.stories.ts","tags":["autodocs","story"],"type":"story"},"example-table--large":{"id":"example-table--large","title":"Example/Table","name":"Large","importPath":"./packages/component/src/Table/Table.stories.ts","tags":["autodocs","story"],"type":"story"},"example-table--small":{"id":"example-table--small","title":"Example/Table","name":"Small","importPath":"./packages/component/src/Table/Table.stories.ts","tags":["autodocs","story"],"type":"story"}}}
